incomfortclient/__init__.py
incomfortclient/py.typed
incomfort_client-0.6.11.dist-info/METADATA
incomfort_client-0.6.11.dist-info/WHEEL
incomfort_client-0.6.11.dist-info/licenses/LICENSE
incomfort_client-0.6.11.dist-info/RECORD
