Metadata-Version: 2.4
Name: incomfort-client
Version: 0.6.11
Summary: An aiohttp-based client for Intergas InComfort/InTouch Lan2RF systems.
License: MIT
License-File: LICENSE
Keywords: incomfort,api,async,client
Author: Jan Bouwhuis
Author-email: jan@jbsoft.nl
Maintainer: Jan Bouwhuis
Maintainer-email: jan@jbsoft.nl
Requires-Python: >=3.9,<4.0
Classifier: Development Status :: 5 - Production/Stable
Classifier: Framework :: AsyncIO
Classifier: Intended Audience :: Developers
Classifier: License :: OSI Approved :: MIT License
Classifier: Natural Language :: English
Classifier: Operating System :: OS Independent
Classifier: Programming Language :: Python :: 3
Classifier: Programming Language :: Python :: 3.9
Classifier: Programming Language :: Python :: 3.10
Classifier: Programming Language :: Python :: 3.11
Classifier: Programming Language :: Python :: 3.12
Classifier: Programming Language :: Python :: 3.13
Classifier: Programming Language :: Python :: 3.14
Classifier: Topic :: Home Automation
Classifier: Topic :: Software Development :: Libraries :: Python Modules
Requires-Dist: aiohttp (>=3.8.1)
Project-URL: Bug Tracker, https://github.com/jbouwh/incomfort-client/issues
Project-URL: Changelog, https://github.com/jbouwh/incomfort-client/releases
Project-URL: Documentation, https://github.com/jbouwh/incomfort-client
Project-URL: Homepage, https://github.com/jbouwh/incomfort-client
Project-URL: Repository, https://github.com/jbouwh/incomfort-client
